clikpython/__init__.py
clikpython/clik.py
clikpython/encrypt.py
clikpython/helpVersion.py
clikpython/json_convert.py
clikpython/keys_init.py
clikpython/menu_functions.py
clikpython/utils.py
python_clik-1.0.dist-info/LICENSE
python_clik-1.0.dist-info/METADATA
python_clik-1.0.dist-info/WHEEL
python_clik-1.0.dist-info/entry_points.txt
python_clik-1.0.dist-info/top_level.txt
python_clik-1.0.dist-info/RECORD
