Metadata-Version: 2.1
Name: python-clik
Version: 1.0
Summary: A CLI tool to keep your Secret/OAuth Keys Safe
Home-page: https://github.com/MLSA-SRM/Project-CLIK
Author: MLSA SRM
Author-email: contact@msclubsrm.in
License: UNKNOWN
Platform: UNKNOWN
Classifier: Programming Language :: Python :: 3
Classifier: License :: OSI Approved :: MIT License
Classifier: Operating System :: OS Independent
Requires-Python: >=3.6
Requires-Dist: printy
Requires-Dist: cryptography
